premodel/KNN.py
premodel/Linear_Regression.py
premodel/__init__.py
premodel-1.1.dist-info/LICENSE.txt
premodel-1.1.dist-info/METADATA
premodel-1.1.dist-info/WHEEL
premodel-1.1.dist-info/top_level.txt
premodel-1.1.dist-info/RECORD
