Metadata-Version: 2.1
Name: premodel
Version: 1.1
Summary: Pre-built Machine Learning Models
Author: Akshat Sabharwal
Author-email: akshatsabharwal35@gmail.com
License-File: LICENSE.txt
Requires-Dist: numpy
Requires-Dist: matplotlib
Requires-Dist: random2
Requires-Dist: pandas
